conect2py/__init__.py
conect2py/models/AutoCloud.py
conect2py/models/AutoTAC.py
conect2py/models/TAC.py
conect2py/models/TEDA.py
conect2py/models/__init__.py
conect2py/run/__init__.py
conect2py/run/multiple.py
conect2py/run/single.py
conect2py/utils/__init__.py
conect2py/utils/format_save.py
conect2py/utils/metrics.py
conect2py/utils/plots.py
conect2py-0.1.4.dist-info/LICENSE
conect2py-0.1.4.dist-info/METADATA
conect2py-0.1.4.dist-info/WHEEL
conect2py-0.1.4.dist-info/top_level.txt
conect2py-0.1.4.dist-info/RECORD
