Metadata-Version: 2.1
Name: conect2py
Version: 0.1.4
Summary: A python library for data compression using TAC (Tiny Anomaly Compression)
Home-page: https://github.com/conect2ai/Conect2Py-Package
Author: Conect2ai
Author-email: conect2ai@gmail.com
Keywords: TEDA,TAC,Annomaly Detection,Data Compression,IoT,Eccentricity
Classifier: License :: OSI Approved :: MIT License
Classifier: Programming Language :: Python :: 3
License-File: LICENSE
Requires-Dist: numpy >=1.26
Requires-Dist: pandas >=2.0
Requires-Dist: matplotlib >=3.8
Requires-Dist: seaborn >=0.13
Requires-Dist: ipython >=7.34
Requires-Dist: scikit-learn >=1.3
